{
  "name" : "BaseSettlementType",
  "preName" : "",
  "comment" : null,
  "templateGroupName" : "Default",
  "fullColumn" : [ {
    "name" : "id",
    "comment" : null,
    "type" : null,
    "shortType" : null,
    "custom" : false,
    "ext" : { }
  }, {
    "name" : "settlementType",
    "comment" : null,
    "type" : null,
    "shortType" : null,
    "custom" : false,
    "ext" : { }
  } ],
  "pkColumn" : null,
  "otherColumn" : null,
  "savePackageName" : "com.xingji.frameproject.mybatis",
  "savePath" : "./src/main/resources/mapper",
  "saveModelName" : "frameproject"
}